{"nodes": [{"id": "test_tts_interrupt_test_speak_chunked", "label": "test_speak_chunked_sets_is_speaking", "file_type": "code", "source_file": "tests/test_tts_interrupt.py", "source_location": null, "source_url": null, "captured_at": null, "author": null, "contributor": null}, {"id": "test_tts_interrupt_test_sanitize_for_speech", "label": "test_sanitize_for_speech", "file_type": "code", "source_file": "tests/test_tts_interrupt.py", "source_location": null, "source_url": null, "captured_at": null, "author": null, "contributor": null}], "edges": [{"source": "test_tts_interrupt_test_speak_chunked", "target": "modules_voice_io_tts_texttospeech", "relation": "calls", "confidence": "EXTRACTED", "confidence_score": 1.0, "source_file": "tests/test_tts_interrupt.py", "source_location": null, "weight": 1.0}, {"source": "test_tts_interrupt_test_sanitize_for_speech", "target": "modules_voice_io_plugin_sanitize_for_speech", "relation": "calls", "confidence": "EXTRACTED", "confidence_score": 1.0, "source_file": "tests/test_tts_interrupt.py", "source_location": null, "weight": 1.0}, {"source": "test_tts_interrupt_test_speak_chunked", "target": "modules_voice_io_tts_split_sentences", "relation": "calls", "confidence": "EXTRACTED", "confidence_score": 1.0, "source_file": "tests/test_tts_interrupt.py", "source_location": null, "weight": 1.0}, {"source": "modules_voice_io_tts_texttospeech", "target": "modules_voice_io_stt_sttengine", "relation": "semantically_similar_to", "confidence": "INFERRED", "confidence_score": 0.75, "source_file": "tests/test_tts_interrupt.py", "source_location": null, "weight": 0.7}], "hyperedges": []}