{"nodes": [{"id": "gws_client_run", "label": "gws._run", "file_type": "code", "source_file": "modules/workspace_agent/gws_client.py", "source_location": null, "source_url": null, "captured_at": null, "author": null, "contributor": null}, {"id": "gws_client_gmail_list_unread", "label": "gmail_list_unread", "file_type": "code", "source_file": "modules/workspace_agent/gws_client.py", "source_location": null, "source_url": null, "captured_at": null, "author": null, "contributor": null}, {"id": "gws_client_calendar_agenda", "label": "calendar_agenda", "file_type": "code", "source_file": "modules/workspace_agent/gws_client.py", "source_location": null, "source_url": null, "captured_at": null, "author": null, "contributor": null}, {"id": "gws_client_calendar_create_event", "label": "calendar_create_event", "file_type": "code", "source_file": "modules/workspace_agent/gws_client.py", "source_location": null, "source_url": null, "captured_at": null, "author": null, "contributor": null}, {"id": "gws_client_gwserror", "label": "GWSError", "file_type": "code", "source_file": "modules/workspace_agent/gws_client.py", "source_location": null, "source_url": null, "captured_at": null, "author": null, "contributor": null}], "edges": [{"source": "gws_client_gmail_list_unread", "target": "gws_client_run", "relation": "calls", "confidence": "EXTRACTED", "confidence_score": 1.0, "source_file": "modules/workspace_agent/gws_client.py", "source_location": null, "weight": 1.0}, {"source": "gws_client_calendar_agenda", "target": "gws_client_run", "relation": "calls", "confidence": "EXTRACTED", "confidence_score": 1.0, "source_file": "modules/workspace_agent/gws_client.py", "source_location": null, "weight": 1.0}, {"source": "gws_client_calendar_create_event", "target": "gws_client_run", "relation": "calls", "confidence": "EXTRACTED", "confidence_score": 1.0, "source_file": "modules/workspace_agent/gws_client.py", "source_location": null, "weight": 1.0}], "hyperedges": []}